Metadata-Version: 2.1
Name: odoo13-addon-partner-affiliate
Version: 13.0.1.1.0
Summary: Partner Affiliates
Home-page: https://github.com/OCA/partner-contact
Author: Camptocamp, Tecnativa, brain-tec AG, Onestein, Odoo Community Association (OCA)
Author-email: support@odoo-community.org
License: AGPL-3
Platform: UNKNOWN
Classifier: Programming Language :: Python
Classifier: Framework :: Odoo
Classifier: Framework :: Odoo :: 13.0
Classifier: License :: OSI Approved :: GNU Affero General Public License v3
Classifier: Development Status :: 5 - Production/Stable
Requires-Python: >=3.5
Requires-Dist: odoo (<13.1dev,>=13.0a)
